color_detection/__init__.py
color_detection/detect.py
examples/__init__.py
examples/detect_color.py
examples/dominant_color.py
test/__init__.py
test/test_color_detection.py
color_detection_jdla-0.0.3.dist-info/LICENSE
color_detection_jdla-0.0.3.dist-info/METADATA
color_detection_jdla-0.0.3.dist-info/WHEEL
color_detection_jdla-0.0.3.dist-info/top_level.txt
color_detection_jdla-0.0.3.dist-info/RECORD
